netro_python/__init__.py
netro_python_dalla-0.0.7.dist-info/LICENSE
netro_python_dalla-0.0.7.dist-info/METADATA
netro_python_dalla-0.0.7.dist-info/WHEEL
netro_python_dalla-0.0.7.dist-info/top_level.txt
netro_python_dalla-0.0.7.dist-info/RECORD
